hashidf/__init__.py
hashidf/data.txt
hashidf-0.1.2.dist-info/licenses/LICENSE
hashidf-0.1.2.dist-info/METADATA
hashidf-0.1.2.dist-info/WHEEL
hashidf-0.1.2.dist-info/top_level.txt
hashidf-0.1.2.dist-info/RECORD
