Metadata-Version: 2.4
Name: hashidf
Version: 0.1.2
Summary: A utility library for decoding Base64, ROT13, and SHA256 hashes
Home-page: https://github.com/hashidf/hashidf
Author: HashIDF Contributors
Author-email: support@hashidf.org
License: MIT
Classifier: Programming Language :: Python :: 3
Classifier: License :: OSI Approved :: MIT License
Classifier: Operating System :: OS Independent
Classifier: Intended Audience :: Developers
Classifier: Topic :: Software Development :: Libraries :: Python Modules
Requires-Python: >=3.6
License-File: LICENSE
Dynamic: author
Dynamic: author-email
Dynamic: classifier
Dynamic: description
Dynamic: description-content-type
Dynamic: home-page
Dynamic: license
Dynamic: license-file
Dynamic: requires-python
Dynamic: summary
